XmlElement/__init__.py
XmlElement/app.py
XmlElement/xml_element.py
XmlElement-0.3.2.dist-info/LICENSE
XmlElement-0.3.2.dist-info/METADATA
XmlElement-0.3.2.dist-info/WHEEL
XmlElement-0.3.2.dist-info/entry_points.txt
XmlElement-0.3.2.dist-info/top_level.txt
XmlElement-0.3.2.dist-info/RECORD
