Metadata-Version: 2.1
Name: XmlElement
Version: 0.3.2
Summary: A simpler XML writer and xml-to-dict converter
Home-page: https://gitlab.ecmind.ch/open/xmlelement
Author: Roland Koller
Author-email: info@ecmind.ch
Classifier: Programming Language :: Python :: 3
Classifier: License :: OSI Approved :: MIT License
Classifier: Operating System :: OS Independent
Requires-Python: >=3.6
License-File: LICENSE
